src/GUI/__init__.py
src/GUI/helpers.py
src/GUI/main.py
NeuroRuler-1.7.dist-info/LICENSE
NeuroRuler-1.7.dist-info/METADATA
NeuroRuler-1.7.dist-info/WHEEL
NeuroRuler-1.7.dist-info/top_level.txt
NeuroRuler-1.7.dist-info/RECORD
