Metadata-Version: 2.1
Name: NeuroRuler
Version: 1.7
Summary: A program that calculates head circumference from MRI data (.nii, .nii.gz, .nrrd).
Home-page: https://github.com/COMP523TeamD/HeadCircumferenceTool
Download-URL: https://github.com/COMP523TeamD/HeadCircumferenceTool/releases
Author: COMP523 Team D
Author-email: Peifeng He <hankhe@ad.unc.edu>, Madison Lester <madiali@email.unc.edu>, Eric Schneider <eric@cs.unc.edu>, Jesse Wei <jesse@cs.unc.edu>
Project-URL: Homepage, https://github.com/COMP523TeamD/HeadCircumferenceTool
Project-URL: Bug Tracker, https://github.com/COMP523TeamD/HeadCircumferenceTool/issues
Keywords: MRI,NIfTI,NRRD,brain,circumference,PyQt6
Classifier: Programming Language :: Python :: 3
Classifier: License :: OSI Approved :: MIT License
Classifier: Operating System :: OS Independent
Classifier: Intended Audience :: Developers
Classifier: Intended Audience :: Science/Research
Classifier: Topic :: Multimedia :: Graphics
Classifier: Topic :: Software Development :: Libraries :: Python Modules
Requires-Python: >=3.8
License-File: LICENSE
Requires-Dist: setuptools
Requires-Dist: sphinx
Requires-Dist: sphinx-rtd-theme
Requires-Dist: SimpleITK
Requires-Dist: numpy
Requires-Dist: argparse
Requires-Dist: opencv-python
Requires-Dist: pytest
Requires-Dist: PyQt6
Requires-Dist: qimage2ndarray
Requires-Dist: screeninfo
Requires-Dist: black
Requires-Dist: pre-commit
Requires-Dist: build
Requires-Dist: twine
